httpie_zign.py
httpie_zign-0.2.dist-info/DESCRIPTION.rst
httpie_zign-0.2.dist-info/METADATA
httpie_zign-0.2.dist-info/RECORD
httpie_zign-0.2.dist-info/WHEEL
httpie_zign-0.2.dist-info/entry_points.txt
httpie_zign-0.2.dist-info/metadata.json
httpie_zign-0.2.dist-info/top_level.txt
