Metadata-Version: 2.0
Name: httpie-zign
Version: 0.2
Summary: Zign OAuth 2 plugin for HTTPie.
Home-page: https://github.com/zalando-stups/httpie-zign
Author: Henning Jacobs
Author-email: henning.jacobs@zalando.de
License: Apache License 2.0
Keywords: httpie oauth oauth2 stups zign access token
Platform: UNKNOWN
Classifier: Development Status :: 5 - Production/Stable
Classifier: Programming Language :: Python
Classifier: Environment :: Plugins
Classifier: License :: OSI Approved :: Apache Software License
Classifier: Topic :: Internet :: WWW/HTTP
Classifier: Topic :: Utilities
Requires-Dist: httpie (>=0.7.0)
Requires-Dist: stups-zign (>=1.0.17)
